CHANGES.txt
CONTRIBUTORS.txt
MANIFEST.in
README.txt
setup.cfg
setup.py
Products/__init__.py
Products.ATGoogleMaps.egg-info/PKG-INFO
Products.ATGoogleMaps.egg-info/SOURCES.txt
Products.ATGoogleMaps.egg-info/dependency_links.txt
Products.ATGoogleMaps.egg-info/entry_points.txt
Products.ATGoogleMaps.egg-info/namespace_packages.txt
Products.ATGoogleMaps.egg-info/not-zip-safe
Products.ATGoogleMaps.egg-info/paster_plugins.txt
Products.ATGoogleMaps.egg-info/requires.txt
Products.ATGoogleMaps.egg-info/top_level.txt
Products/ATGoogleMaps/#widget.py#
Products/ATGoogleMaps/LICENSE.GPL
Products/ATGoogleMaps/LICENSE.txt
Products/ATGoogleMaps/README.txt
Products/ATGoogleMaps/__init__.py
Products/ATGoogleMaps/config.py
Products/ATGoogleMaps/configure.zcml
Products/ATGoogleMaps/field.py
Products/ATGoogleMaps/refresh.txt
Products/ATGoogleMaps/validator.py
Products/ATGoogleMaps/version.txt
Products/ATGoogleMaps/widget.py
Products/ATGoogleMaps/browser/__init__.py
Products/ATGoogleMaps/browser/configure.zcml
Products/ATGoogleMaps/content/GMap.py
Products/ATGoogleMaps/content/GMarker.py
Products/ATGoogleMaps/content/GPolyline.py
Products/ATGoogleMaps/content/__init__.py
Products/ATGoogleMaps/content/configure.zcml
Products/ATGoogleMaps/i18n/atgooglemaps-ja.mo
Products/ATGoogleMaps/i18n/atgooglemaps-ja.po
Products/ATGoogleMaps/i18n/atgooglemaps-plone-ja.mo
Products/ATGoogleMaps/i18n/atgooglemaps-plone-ja.po
Products/ATGoogleMaps/i18n/atgooglemaps-plone.pot
Products/ATGoogleMaps/i18n/atgooglemaps.pot
Products/ATGoogleMaps/interfaces/__init__.py
Products/ATGoogleMaps/locales/atgooglemaps-plone.pot
Products/ATGoogleMaps/locales/atgooglemaps.pot
Products/ATGoogleMaps/locales/ja/LC_MESSAGES/atgooglemaps-plone.mo
Products/ATGoogleMaps/locales/ja/LC_MESSAGES/atgooglemaps-plone.po
Products/ATGoogleMaps/locales/ja/LC_MESSAGES/atgooglemaps.mo
Products/ATGoogleMaps/locales/ja/LC_MESSAGES/atgooglemaps.po
Products/ATGoogleMaps/portlets/__init__.py
Products/ATGoogleMaps/portlets/configure.zcml
Products/ATGoogleMaps/profiles/default/cssregistry.xml
Products/ATGoogleMaps/profiles/default/factorytool.xml
Products/ATGoogleMaps/profiles/default/jsregistry.xml
Products/ATGoogleMaps/profiles/default/metadata.xml
Products/ATGoogleMaps/profiles/default/portlets.xml
Products/ATGoogleMaps/profiles/default/rolemap.xml
Products/ATGoogleMaps/profiles/default/skins.xml
Products/ATGoogleMaps/profiles/default/types.xml
