Metadata-Version: 1.0
Name: Products.ATGoogleMaps
Version: 0.7
Summary: ATContentTypes-based Google Maps v3 product for Plone.
Home-page: http://plone.org/products/atgooglemaps
Author: Takanori Suzuki
Author-email: takanori@takanory.net
License: GPL
Keywords: Plone ATGoogleMaps Google Maps Geospotical
Platform: UNKNOWN
Classifier: Framework :: Plone
Classifier: Intended Audience :: Developers
Classifier: Topic :: Software Development :: Libraries :: Python Modules
Classifier: License :: OSI Approved :: GNU General Public License (GPL)
